tests/__init__.py
tests/mocks.py
tests/test_xrennerjsonnlp.py
xrennerjsonnlp/__init__.py
xrennerjsonnlp/server.py
xrennerjsonnlp-0.0.5.dist-info/LICENSE
xrennerjsonnlp-0.0.5.dist-info/METADATA
xrennerjsonnlp-0.0.5.dist-info/WHEEL
xrennerjsonnlp-0.0.5.dist-info/top_level.txt
xrennerjsonnlp-0.0.5.dist-info/RECORD
