Metadata-Version: 2.1
Name: xrennerjsonnlp
Version: 0.0.5
Summary: The Python Xrenner JSON-NLP package
Home-page: https://github.com/dcavar/Xrenner-JSON-NLP
Author: Damir Cavar, Oren Baldinger, Maanvitha Gongalla, Anurag Kumar, Murali Kammili, Boli Fang
Author-email: damir@cavar.me
License: UNKNOWN
Platform: UNKNOWN
Classifier: Programming Language :: Python :: 3
Classifier: License :: OSI Approved :: Apache Software License
Classifier: Operating System :: OS Independent
Requires-Dist: xrenner (>=2.0.2.0)
Requires-Dist: pyjsonnlp (>=0.2.11)
Requires-Dist: beautifulsoup4 (>=4.6.3)
Requires-Dist: nltk (>=3.4)
Requires-Dist: python-dotenv (>=0.10.1)
